CHANGES.txt
LICENSE.txt
bootstrap.py
buildout.cfg
setup.py
src/lovely/__init__.py
src/lovely.persistent.egg-info/PKG-INFO
src/lovely.persistent.egg-info/SOURCES.txt
src/lovely.persistent.egg-info/dependency_links.txt
src/lovely.persistent.egg-info/namespace_packages.txt
src/lovely.persistent.egg-info/not-zip-safe
src/lovely.persistent.egg-info/requires.txt
src/lovely.persistent.egg-info/top_level.txt
src/lovely/persistent/LICENSE.txt
src/lovely/persistent/README.txt
src/lovely/persistent/__init__.py
src/lovely/persistent/app.py
src/lovely/persistent/tests.py
