Metadata-Version: 1.0
Name: lovely.persistent
Version: 0.1.1
Summary: improved ZODB persistence
Home-page: http://launchpad.net/lovely.persistent
Author: Lovely Systems GmbH
Author-email: office@lovelysystems.com
License: ZPL 2.1
Keywords: persistent zope zope3
Platform: UNKNOWN
Classifier: Development Status :: 4 - Beta
Classifier: Intended Audience :: Developers
Classifier: License :: OSI Approved :: Zope Public License
Classifier: Topic :: Software Development :: Libraries :: Python Modules
